genauth/AuthenticationClient.py
genauth/GenAuthException.py
genauth/ManagementClient.py
genauth/ManagementTokenProvider.py
genauth/__init__.py
genauth/constants.py
genauth/exceptions.py
genauth/version.py
genauth/http/AuthenticationHttpClient.py
genauth/http/ManagementHttpClient.py
genauth/http/ProtocolHttpClient.py
genauth/http/__init__.py
genauth/utils/__init__.py
genauth/utils/signatureComposer.py
genauth/utils/wss.py
genauth-5.1.0.dist-info/LICENSE
genauth-5.1.0.dist-info/METADATA
genauth-5.1.0.dist-info/WHEEL
genauth-5.1.0.dist-info/top_level.txt
genauth-5.1.0.dist-info/RECORD
