Metadata-Version: 2.1
Name: genauth
Version: 5.1.0
Summary: Python SDK for GenAuth
Home-page: https://github.com/GenAuth-Official/genauth-py-sdk
Author: GenAuth
Author-email: dev@genauth.ai
Maintainer: GenAuth
Maintainer-email: dev@genauth.ai
Keywords: GenAuth sso AaaS IdaaS
Classifier: Programming Language :: Python :: 2
Classifier: Programming Language :: Python :: 2.7
Classifier: Programming Language :: Python :: 3
Classifier: Programming Language :: Python :: 3.2
Classifier: Programming Language :: Python :: 3.3
Classifier: Programming Language :: Python :: 3.4
Classifier: Programming Language :: Python :: 3.5
Classifier: Programming Language :: Python :: 3.6
Classifier: Programming Language :: Python :: 3.7
Classifier: Programming Language :: Python :: 3.8
Classifier: Programming Language :: Python :: 3.9
Classifier: Programming Language :: Python :: 3.10
License-File: LICENSE
Requires-Dist: requests
Requires-Dist: pyjwt
